LICENSE
MANIFEST.in
README.rst
buildout.cfg
develop.cfg
pyproject.toml
requirements.txt
setup.py
version.txt
bob/__init__.py
bob.db.base.egg-info/PKG-INFO
bob.db.base.egg-info/SOURCES.txt
bob.db.base.egg-info/dependency_links.txt
bob.db.base.egg-info/entry_points.txt
bob.db.base.egg-info/not-zip-safe
bob.db.base.egg-info/requires.txt
bob.db.base.egg-info/top_level.txt
bob/db/__init__.py
bob/db/base/__init__.py
bob/db/base/annotations.py
bob/db/base/database.py
bob/db/base/driver.py
bob/db/base/file.py
bob/db/base/manage.py
bob/db/base/sqlalchemy_migration.py
bob/db/base/utils.py
bob/db/base/data/eyecenter.pos
bob/db/base/data/idiap.pos
bob/db/base/data/json.pos
bob/db/base/data/named.pos
bob/db/base/data/test_db.sql3
bob/db/base/script/__init__.py
bob/db/base/script/db.py
bob/db/base/script/dbmanage.py
bob/db/base/tests/__init__.py
bob/db/base/tests/test_database.py
bob/db/base/tests/test_driver.py
bob/db/base/tests/test_sql.py
bob/db/base/tests/sample/__init__.py
bob/db/base/tests/sample/driver.py
bob/db/base/tests/sample/models.py
bob/db/base/tests/sample/query.py
bob/db/base/tests/sample/data/dir1/sample1-1.png
bob/db/base/tests/sample/data/dir1/sample1-1.txt
bob/db/base/tests/sample/data/dir1/sample1-2.png
bob/db/base/tests/sample/data/dir1/sample1-2.txt
bob/db/base/tests/sample/data/dir2/sample2-1.png
bob/db/base/tests/sample/data/dir2/sample2-1.txt
bob/db/base/tests/sample/data/dir2/sample2-2.png
bob/db/base/tests/sample/data/dir2/sample2-2.txt
bob/db/base/tests/sample/data/dir3/sample3-1.png
bob/db/base/tests/sample/data/dir3/sample3-1.txt
bob/db/base/tests/sample/data/dir3/sample3-2.png
bob/db/base/tests/sample/data/dir3/sample3-2.txt
doc/conf.py
doc/development-guide.rst
doc/extend.rst
doc/index.rst
doc/links.rst
doc/py_api.rst
doc/user-guide.rst